llm_md/__init__.py
llm_md/cli.py
llm_md/generator.py
llm_md/parser.py
llm_md/scanner.py
llm_md-0.1.0.dist-info/licenses/LICENSE
llm_md-0.1.0.dist-info/METADATA
llm_md-0.1.0.dist-info/WHEEL
llm_md-0.1.0.dist-info/entry_points.txt
llm_md-0.1.0.dist-info/top_level.txt
llm_md-0.1.0.dist-info/RECORD
