Metadata-Version: 2.4
Name: llm-md
Version: 0.1.0
Summary: CLI tool for generating LLM context from GitHub repositories
Requires-Python: >=3.13
License-File: LICENSE
Requires-Dist: click>=8.2.1
Requires-Dist: pathspec>=0.12.1
Dynamic: license-file
